usls/__init__.py
usls/cli.py
usls/src/__init__.py
usls/src/labelling.py
usls/src/run.py
usls/src/spider.py
usls/src/utils.py
usls/src/video_tools.py
usls-0.2023.0.dist-info/LICENSE
usls-0.2023.0.dist-info/METADATA
usls-0.2023.0.dist-info/WHEEL
usls-0.2023.0.dist-info/entry_points.txt
usls-0.2023.0.dist-info/top_level.txt
usls-0.2023.0.dist-info/RECORD
