Metadata-Version: 2.1
Name: usls
Version: 0.2023.0
Summary: Useless CV toolkits
Home-page: https://github.com/jamjamjon/usls
Author: jamjamjon
License: GPL-3.0
Requires-Python: >=3.9
License-File: LICENSE
Requires-Dist: baiduspider
Requires-Dist: numpy
Requires-Dist: omegaconf
Requires-Dist: opencv-python
Requires-Dist: packaging
Requires-Dist: Pillow
Requires-Dist: PyYAML
Requires-Dist: requests
Requires-Dist: rich
Requires-Dist: tqdm
